{
  "$schema": "./node_modules/@angular/service-worker/config/schema.json",
  "index": "/index.html",
  "assetGroups": [
    {
      "name": "app",
      "installMode": "prefetch",
      "resources": {
        "files": [
          "/favicon.ico",
          "/index.html",
          "/manifest.webmanifest",
          "/*.css",
          "/*.js"
        ],
        "urls": [
          "https://cdn.jsdelivr.net/npm/bootstrap@5.0.2/dist/css/bootstrap.min.css"
        ]
      }
    },
    {
      "name": "assets",
      "installMode": "lazy",
      "updateMode": "prefetch",
      "resources": {
        "files": [
          "/assets/**",
          "/*.(svg|cur|jpg|jpeg|png|apng|webp|avif|gif|otf|ttf|woff|woff2)"
        ],
        "urls": [
          "https://robohash.org/api/**"
        ]
      }
    }
  ],
  "dataGroups": [
    {
      "name": "swr-api",
      "urls": [
        "https://swapi.dev/api/**"
      ],
      "cacheConfig": {
        "maxSize": 10,
        "maxAge": "1h",
        "timeout": "1s",
        "strategy": "performance"
      }
    }
  ]
}